README.rst
setup.py
fabliip/__init__.py
fabliip/decorators.py
fabliip/file.py
fabliip/releases.py
fabliip/signals.py
fabliip/utils.py
fabliip/version.py
fabliip.egg-info/PKG-INFO
fabliip.egg-info/SOURCES.txt
fabliip.egg-info/dependency_links.txt
fabliip.egg-info/requires.txt
fabliip.egg-info/top_level.txt
fabliip/database/__init__.py
fabliip/database/mysql.py
fabliip/database/pgsql.py
fabliip/drupal/__init__.py
fabliip/vcs/__init__.py
fabliip/vcs/git.py