Metadata-Version: 1.0
Name: fabliip
Version: 0.3.8
Summary: Set of Fabric functions to help deploying websites.
Home-page: https://github.com/sephii/fabliip
Author: Sylvain Fankhauser
Author-email: sylvain.fankhauser@liip.ch
License: UNKNOWN
Platform: UNKNOWN
